bionic_writer-0.1.0.dist-info/METADATA
bionic_writer-0.1.0.dist-info/WHEEL
bionic_writer-0.1.0.dist-info/license_files/LICENSE
bionic_writer/__init__.py
bionic_writer/__init__.pyi
bionic_writer/py.typed
bionic_writer/bionic_writer.pypy39-pp73-aarch64-linux-gnu.so
bionic_writer-0.1.0.dist-info/RECORD
