Metadata-Version: 2.1
Name: bionic-writer
Version: 0.1.0
Classifier: Intended Audience :: Developers
Classifier: Operating System :: MacOS
Classifier: Operating System :: Microsoft :: Windows
Classifier: Operating System :: POSIX :: Linux
Classifier: Programming Language :: Rust
Classifier: Programming Language :: Python
Classifier: Programming Language :: Python :: 3
Classifier: Programming Language :: Python :: 3.8
Classifier: Programming Language :: Python :: 3.9
Classifier: Programming Language :: Python :: 3.10
Classifier: Programming Language :: Python :: 3.11
Classifier: Programming Language :: Python :: 3.12
Classifier: Programming Language :: Python :: Implementation :: CPython
License-File: LICENSE
Summary: Write Bionic Reading text with Python.
Keywords: bionicreading,bionic-reading,text-formatter
Home-Page: https://github.com/u8slvn/bionic-writer
Author: u8slvn <u8slvn@gmail.com>
Author-email: u8slvn <u8slvn@gmail.com>
License: MIT
Requires-Python: >=3.8
Project-URL: Source Code, https://github.com/u8slvn/bionic-writer
